eBoruta/__about__.py
eBoruta/__init__.py
eBoruta/algorithm.py
eBoruta/base.py
eBoruta/callbacks.py
eBoruta/containers.py
eBoruta/dataprep.py
eBoruta/utils.py
eboruta-0.3.dist-info/METADATA
eboruta-0.3.dist-info/WHEEL
eboruta-0.3.dist-info/licenses/LICENCE
eboruta-0.3.dist-info/RECORD
